setup.cfg
setup.py
stackctl/__init__.py
stackctl/cmds.py
stackctl/errors.py
stackctl/nova_wrapper.py
stackctl/ssh.py
stackctl/stackctl.py
stackctl.egg-info/PKG-INFO
stackctl.egg-info/SOURCES.txt
stackctl.egg-info/dependency_links.txt
stackctl.egg-info/entry_points.txt
stackctl.egg-info/requires.txt
stackctl.egg-info/top_level.txt