Metadata-Version: 1.1
Name: stackctl
Version: 0.2.0
Summary: Wrapper around python-novaclient to facilitate cloning and maintianing openstack instances.
Home-page: https://github.com/Kazanz/stackctl
Author: Zach Kazanski
Author-email: kazanski.zachary@gmail.com
License: UNKNOWN
Keywords: openstack
Platform: UNKNOWN
Classifier: Programming Language :: Python
Classifier: Intended Audience :: Developers
Classifier: Operating System :: OS Independent
Classifier: License :: OSI Approved :: MIT License
Classifier: Programming Language :: Python :: 2.7
